{"nodes": [{"id": "src_composables_usetaxcalculation_ts", "label": "useTaxCalculation.ts", "file_type": "code", "source_file": "src\\composables\\useTaxCalculation.ts", "source_location": "L1"}, {"id": "composables_usetaxcalculation_tax_group_rates", "label": "TAX_GROUP_RATES", "file_type": "code", "source_file": "src\\composables\\useTaxCalculation.ts", "source_location": "L4"}, {"id": "composables_usetaxcalculation_round2", "label": "round2()", "file_type": "code", "source_file": "src\\composables\\useTaxCalculation.ts", "source_location": "L24"}, {"id": "composables_usetaxcalculation_itemtaxresult", "label": "ItemTaxResult", "file_type": "code", "source_file": "src\\composables\\useTaxCalculation.ts", "source_location": "L28"}, {"id": "composables_usetaxcalculation_taxsummary", "label": "TaxSummary", "file_type": "code", "source_file": "src\\composables\\useTaxCalculation.ts", "source_location": "L35"}, {"id": "composables_usetaxcalculation_initgroupmap", "label": "initGroupMap()", "file_type": "code", "source_file": "src\\composables\\useTaxCalculation.ts", "source_location": "L46"}, {"id": "composables_usetaxcalculation_fiscalcalcconfig", "label": "FiscalCalcConfig", "file_type": "code", "source_file": "src\\composables\\useTaxCalculation.ts", "source_location": "L53"}, {"id": "composables_usetaxcalculation_usetaxcalculation", "label": "useTaxCalculation()", "file_type": "code", "source_file": "src\\composables\\useTaxCalculation.ts", "source_location": "L60"}], "edges": [{"source": "src_composables_usetaxcalculation_ts", "target": "c_wamp64_www_wimrux_finances_wimrux_app_src_types_index_ts", "relation": "imports_from", "context": "import", "confidence": "EXTRACTED", "source_file": "src\\composables\\useTaxCalculation.ts", "source_location": "L1", "weight": 1.0}, {"source": "src_composables_usetaxcalculation_ts", "target": "types_index_taxgroup", "relation": "imports", "context": "import", "confidence": "EXTRACTED", "source_file": "src\\composables\\useTaxCalculation.ts", "source_location": "L1", "weight": 1.0}, {"source": "src_composables_usetaxcalculation_ts", "target": "types_index_pricemode", "relation": "imports", "context": "import", "confidence": "EXTRACTED", "source_file": "src\\composables\\useTaxCalculation.ts", "source_location": "L1", "weight": 1.0}, {"source": "src_composables_usetaxcalculation_ts", "target": "types_index_paymenttype", "relation": "imports", "context": "import", "confidence": "EXTRACTED", "source_file": "src\\composables\\useTaxCalculation.ts", "source_location": "L1", "weight": 1.0}, {"source": "src_composables_usetaxcalculation_ts", "target": "types_index_invoiceitem", "relation": "imports", "context": "import", "confidence": "EXTRACTED", "source_file": "src\\composables\\useTaxCalculation.ts", "source_location": "L1", "weight": 1.0}, {"source": "src_composables_usetaxcalculation_ts", "target": "types_index_taxgroupconfig", "relation": "imports", "context": "import", "confidence": "EXTRACTED", "source_file": "src\\composables\\useTaxCalculation.ts", "source_location": "L1", "weight": 1.0}, {"source": "src_composables_usetaxcalculation_ts", "target": "types_index_stampdutythreshold", "relation": "imports", "context": "import", "confidence": "EXTRACTED", "source_file": "src\\composables\\useTaxCalculation.ts", "source_location": "L1", "weight": 1.0}, {"source": "src_composables_usetaxcalculation_ts", "target": "composables_usetaxcalculation_tax_group_rates", "relation": "contains", "confidence": "EXTRACTED", "source_file": "src\\composables\\useTaxCalculation.ts", "source_location": "L4", "weight": 1.0}, {"source": "src_composables_usetaxcalculation_ts", "target": "composables_usetaxcalculation_round2", "relation": "contains", "confidence": "EXTRACTED", "source_file": "src\\composables\\useTaxCalculation.ts", "source_location": "L24", "weight": 1.0}, {"source": "src_composables_usetaxcalculation_ts", "target": "composables_usetaxcalculation_itemtaxresult", "relation": "contains", "confidence": "EXTRACTED", "source_file": "src\\composables\\useTaxCalculation.ts", "source_location": "L28", "weight": 1.0}, {"source": "src_composables_usetaxcalculation_ts", "target": "composables_usetaxcalculation_taxsummary", "relation": "contains", "confidence": "EXTRACTED", "source_file": "src\\composables\\useTaxCalculation.ts", "source_location": "L35", "weight": 1.0}, {"source": "src_composables_usetaxcalculation_ts", "target": "composables_usetaxcalculation_initgroupmap", "relation": "contains", "confidence": "EXTRACTED", "source_file": "src\\composables\\useTaxCalculation.ts", "source_location": "L46", "weight": 1.0}, {"source": "src_composables_usetaxcalculation_ts", "target": "composables_usetaxcalculation_fiscalcalcconfig", "relation": "contains", "confidence": "EXTRACTED", "source_file": "src\\composables\\useTaxCalculation.ts", "source_location": "L53", "weight": 1.0}, {"source": "src_composables_usetaxcalculation_ts", "target": "composables_usetaxcalculation_usetaxcalculation", "relation": "contains", "confidence": "EXTRACTED", "source_file": "src\\composables\\useTaxCalculation.ts", "source_location": "L60", "weight": 1.0}], "raw_calls": [{"caller_nid": "composables_usetaxcalculation_round2", "callee": "round", "is_member_call": true, "source_file": "src\\composables\\useTaxCalculation.ts", "source_location": "L25"}, {"caller_nid": "composables_usetaxcalculation_initgroupmap", "callee": "forEach", "is_member_call": true, "source_file": "src\\composables\\useTaxCalculation.ts", "source_location": "L49"}]}